trezorpass/__init__.py
trezorpass/appdata.py
trezorpass/cli.py
trezorpass/crypto.py
trezorpass/utils.py
trezorpass/client/__init__.py
trezorpass/client/client.py
trezorpass/client/ui.py
trezorpass/helpers/__init__.py
trezorpass/helpers/client.py
trezorpass/helpers/entry.py
trezorpass/store/__init__.py
trezorpass/store/containers.py
trezorpass/store/entry.py
trezorpass/store/keychain.py
trezorpass/store/store.py
trezorpass/store/tag.py
trezorpass/store/sources/__init__.py
trezorpass/store/sources/dropbox_source.py
trezorpass/store/sources/file_source.py
trezorpass/store/sources/source.py
trezor_pass-1.5.1.dist-info/LICENSE
trezor_pass-1.5.1.dist-info/METADATA
trezor_pass-1.5.1.dist-info/WHEEL
trezor_pass-1.5.1.dist-info/entry_points.txt
trezor_pass-1.5.1.dist-info/top_level.txt
trezor_pass-1.5.1.dist-info/RECORD
