Metadata-Version: 2.1
Name: trezor-pass
Version: 1.5.1
Summary: Trezor Password Manager Command-Line interface
Home-page: https://github.com/pilartomas/trezor-password-manager-cli
Author: Tomas Pilar
Author-email: thomas7pilar@gmail.com
Project-URL: Bug Reports, https://github.com/pilartomas/trezor-password-manager-cli/issues
Keywords: trezor,password
Classifier: Programming Language :: Python :: 3
Classifier: Operating System :: OS Independent
Classifier: License :: OSI Approved :: GNU Lesser General Public License v3 (LGPLv3)
Requires-Python: >=3.10, <4
License-File: LICENSE
Requires-Dist: trezor
Requires-Dist: cryptography
Requires-Dist: inquirerpy
Requires-Dist: dropbox
Requires-Dist: appdirs
Requires-Dist: pyperclip
Requires-Dist: prompt-toolkit
